_pyohrli.cp311-win32.pyd
zimtohrli.py
zimtohrli-0.2.1.post1.dist-info/licenses/LICENSE
zimtohrli-0.2.1.post1.dist-info/METADATA
zimtohrli-0.2.1.post1.dist-info/WHEEL
zimtohrli-0.2.1.post1.dist-info/top_level.txt
zimtohrli-0.2.1.post1.dist-info/RECORD
