Metadata-Version: 2.4
Name: zimtohrli
Version: 0.2.1.post1
Summary: Psychoacoustic perceptual metric that quantifies the human observable difference in two audio signals in the proximity of just-noticeable-differences
Author: Martin Bruse, Jyrki Alakuijala
Author-email: zond@google.com, jyrki@google.com
Requires-Python: >=3.10
License-File: LICENSE
Requires-Dist: numpy>=1.20.0
Dynamic: author
Dynamic: author-email
Dynamic: description
Dynamic: description-content-type
Dynamic: license-file
Dynamic: requires-dist
Dynamic: requires-python
Dynamic: summary
